[
  { "zone": "colinabartlett.com",
    "records": [
      { "type": "A", "name": "", "ttl": 60, "value": "104.236.62.188" },
      { "type": "A", "name": "do", "ttl": 60, "value": "104.236.62.188" },
      { "type": "A", "name": "home", "ttl": 60, "value": "100.37.202.160" },
      { "type": "CNAME", "name": "calendar", "ttl": 3600, "value": "ghs.googlehosted.com" },
      { "type": "CNAME", "name": "deployhooks", "ttl": 3600, "value": "cbartlett-deploy-hook-forker.herokuapp.com" },
      { "type": "CNAME", "name": "docs", "ttl": 3600, "value": "ghs.googlehosted.com" },
      { "type": "CNAME", "name": "mail", "ttl": 3600, "value": "ghs.googlehosted.com" },
      { "type": "CNAME", "name": "sites", "ttl": 3600, "value": "ghs.googlehosted.com" },
      { "type": "MX", "name": "", "ttl": 3600, "value": "alt1.aspmx.l.google.com", "prio": 5 },
      { "type": "MX", "name": "", "ttl": 3600, "value": "alt2.aspmx.l.google.com", "prio": 5 },
      { "type": "MX", "name": "", "ttl": 3600, "value": "aspmx2.googlemail.com", "prio": 10 },
      { "type": "MX", "name": "", "ttl": 3600, "value": "aspmx3.googlemail.com", "prio": 10 },
      { "type": "MX", "name": "", "ttl": 3600, "value": "aspmx.l.google.com", "prio": 1 },
      { "type": "SPF", "name": "", "ttl": 3600, "value": "v=spf1 a include:_spf.google.com -all" },
      { "type": "URL", "name": "www", "ttl": 60, "value": "http://colinabartlett.com" }
    ]
  }
]
